[
  {
    "id": 1,
    "translations": {
      "en": {
        "text": "the supermarket",
        "phonetic": "/ˈsuːpərˌmɑːrkɪt/",
        "synonyms": [
          "grocery store"
        ],
        "examples": [
          "I’m going to the supermarket after work."
        ]
      },
      "de": {
        "text": "Der Supermarkt",
        "phonetic": "/ˈzuːpɐˌmaʁkt/",
        "synonyms": [
          "Lebensmittelladen"
        ],
        "examples": [
          "Ich gehe nach der Arbeit in den Supermarkt."
        ]
      },
      "es": {
        "text": "el supermercado",
        "phonetic": "/supeɾmeɾˈkaðo/",
        "synonyms": [
          "tienda de comestibles"
        ],
        "examples": [
          "Voy al supermercado después del trabajo."
        ]
      }
    },
    "tags": [
      "noun",
      "shopping"
    ],
    "level": "A1"
  },
  {
    "id": 2,
    "translations": {
      "en": {
        "text": "closed",
        "phonetic": "/kloʊzd/",
        "synonyms": [
          "shut"
        ],
        "examples": [
          "The store is closed on Sundays."
        ]
      },
      "de": {
        "text": "geschlossen",
        "phonetic": "/ɡəˈʃlɔsən/",
        "synonyms": [
          "zu"
        ],
        "examples": [
          "Der Laden ist sonntags geschlossen."
        ]
      },
      "es": {
        "text": "cerrado",
        "phonetic": "/seˈraðo/",
        "synonyms": [
          "clausurado"
        ],
        "examples": [
          "La tienda está cerrada los domingos."
        ]
      }
    },
    "tags": [
      "adjective",
      "state"
    ],
    "level": "A1"
  },
  {
    "id": 3,
    "translations": {
      "en": {
        "text": "the bank",
        "phonetic": "/bæŋk/",
        "synonyms": [
          "financial institution"
        ],
        "examples": [
          "I have an appointment at the bank."
        ]
      },
      "de": {
        "text": "Die Bank",
        "phonetic": "/baŋk/",
        "synonyms": [
          "Kreditinstitut"
        ],
        "examples": [
          "Ich bin gerade in der Bank."
        ]
      },
      "es": {
        "text": "el banco",
        "phonetic": "/ˈbaŋko/",
        "synonyms": [
          "entidad financiera"
        ],
        "examples": [
          "Estoy en el banco."
        ]
      }
    },
    "tags": [
      "noun",
      "money"
    ],
    "level": "A1"
  },
  {
    "id": 4,
    "translations": {
      "en": {
        "text": "the street",
        "phonetic": "/striːt/",
        "synonyms": [
          "road"
        ],
        "examples": [
          "There’s a café across the street."
        ]
      },
      "de": {
        "text": "Die Straße",
        "phonetic": "/ˈʃtʁaːsə/",
        "synonyms": [
          "Straße",
          "Weg"
        ],
        "examples": [
          "Ich warte auf dich auf der Straße."
        ]
      },
      "es": {
        "text": "la calle",
        "phonetic": "/ˈkaʝe/",
        "synonyms": [
          "vía"
        ],
        "examples": [
          "La tienda está al final de la calle."
        ]
      }
    },
    "tags": [
      "noun",
      "city"
    ],
    "level": "A1"
  },
  {
    "id": 5,
    "translations": {
      "en": {
        "text": "the bathroom",
        "phonetic": "/ˈbæθˌruːm/",
        "synonyms": [
          "restroom"
        ],
        "examples": [
          "Where is the bathroom?"
        ]
      },
      "de": {
        "text": "Das Bad",
        "phonetic": "/baːt/",
        "synonyms": [
          "Badezimmer"
        ],
        "examples": [
          "Wo ist das Bad?"
        ]
      },
      "es": {
        "text": "el baño",
        "phonetic": "/ˈbaɲo/",
        "synonyms": [
          "baño",
          "servicio"
        ],
        "examples": [
          "¿Dónde está el baño?"
        ]
      }
    },
    "tags": [
      "noun",
      "house"
    ],
    "level": "A1"
  },
  {
    "id": 6,
    "translations": {
      "en": {
        "text": "the hospital",
        "phonetic": "/ˈhɑːspɪtəl/",
        "synonyms": [
          "medical center"
        ],
        "examples": [
          "She works at the hospital downtown."
        ]
      },
      "de": {
        "text": "Das Krankenhaus",
        "phonetic": "/ˈkʁaŋkn̩ˌhaʊs/",
        "synonyms": [
          "medizinisches Zentrum"
        ],
        "examples": [
          "Er arbeitet im Krankenhaus."
        ]
      },
      "es": {
        "text": "el hospital",
        "phonetic": "/ospiˈtal/",
        "synonyms": [
          "centro médico"
        ],
        "examples": [
          "Trabajo en el hospital del centro."
        ]
      }
    },
    "tags": [
      "noun",
      "health"
    ],
    "level": "A1"
  },
  {
    "id": 7,
    "translations": {
      "en": {
        "text": "the museum",
        "phonetic": "/mjuˈziːəm/",
        "synonyms": [
          "gallery"
        ],
        "examples": [
          "We visited the art museum yesterday."
        ]
      },
      "de": {
        "text": "Das Museum",
        "phonetic": "/muˈzeːʊm/",
        "synonyms": [
          "Ausstellungshaus"
        ],
        "examples": [
          "Wir waren gestern im Museum."
        ]
      },
      "es": {
        "text": "el museo",
        "phonetic": "/muˈseo/",
        "synonyms": [
          "galería"
        ],
        "examples": [
          "Ayer visitamos el museo."
        ]
      }
    },
    "tags": [
      "place",
      "culture"
    ],
    "level": "A1"
  },
  {
    "id": 8,
    "translations": {
      "en": {
        "text": "your",
        "phonetic": "/jʊr/",
        "synonyms": [
          ""
        ],
        "examples": [
          "Is this your jacket?"
        ]
      },
      "de": {
        "text": "dein",
        "phonetic": "/daɪ̯n/",
        "synonyms": [
          "deine"
        ],
        "examples": [
          "Ist das dein Buch?"
        ]
      },
      "es": {
        "text": "tu",
        "phonetic": "/tu/",
        "synonyms": [
          "tuyo (adj.)"
        ],
        "examples": [
          "¿Es este tu abrigo?"
        ]
      }
    },
    "tags": [
      "pronoun",
      "possessive",
      "grammar"
    ],
    "level": "A1"
  },
  {
    "id": 9,
    "translations": {
      "en": {
        "text": "the train",
        "phonetic": "/treɪn/",
        "synonyms": [
          "railway train"
        ],
        "examples": [
          "The train arrives at six o’clock."
        ]
      },
      "de": {
        "text": "Der Zug",
        "phonetic": "/tsuːk/",
        "synonyms": [
          "Bahn"
        ],
        "examples": [
          "Der Zug kommt um sechs Uhr an."
        ]
      },
      "es": {
        "text": "el tren",
        "phonetic": "/tɾen/",
        "synonyms": [
          "ferrocarril"
        ],
        "examples": [
          "El tren llega a las seis."
        ]
      }
    },
    "tags": [
      "transport",
      "noun"
    ],
    "level": "A1"
  },
  {
    "id": 10,
    "translations": {
      "en": {
        "text": "the bus",
        "phonetic": "/bʌs/",
        "synonyms": [
          "coach"
        ],
        "examples": [
          "We took the bus to the city center."
        ]
      },
      "de": {
        "text": "Der Bus",
        "phonetic": "/bʊs/",
        "synonyms": [
          "Omnibus"
        ],
        "examples": [
          "Wir sind mit dem Bus ins Zentrum gefahren."
        ]
      },
      "es": {
        "text": "el autobús",
        "phonetic": "/autoˈβus/",
        "synonyms": [
          "ómnibus",
          "bus"
        ],
        "examples": [
          "Tomamos el autobús al centro."
        ]
      }
    },
    "tags": [
      "transport",
      "noun"
    ],
    "level": "A1"
  },
  {
    "id": 11,
    "translations": {
      "en": {
        "text": "the airport",
        "phonetic": "/ˈɛərˌpɔːrt/",
        "synonyms": [
          "airfield"
        ],
        "examples": [
          "My flight leaves from the main airport."
        ]
      },
      "de": {
        "text": "Der Flughafen",
        "phonetic": "/ˈfluːkˌhaːfən/",
        "synonyms": [
          "Airport"
        ],
        "examples": [
          "Mein Flug geht vom Flughafen Berlin."
        ]
      },
      "es": {
        "text": "el aeropuerto",
        "phonetic": "/aeɾoˈpweɾto/",
        "synonyms": [
          "terminal aérea"
        ],
        "examples": [
          "Mi vuelo sale del aeropuerto principal."
        ]
      }
    },
    "tags": [
      "noun",
      "transport"
    ],
    "level": "A1"
  },
  {
    "id": 12,
    "translations": {
      "en": {
        "text": "the ticket",
        "phonetic": "/ˈtɪkɪt/",
        "synonyms": [
          "pass"
        ],
        "examples": [
          "I bought a train ticket online."
        ]
      },
      "de": {
        "text": "Das Ticket",
        "phonetic": "/ˈtɪkɛt/",
        "synonyms": [
          "Fahrkarte"
        ],
        "examples": [
          "Ich habe das Ticket online gekauft."
        ]
      },
      "es": {
        "text": "el boleto",
        "phonetic": "/boˈleto/",
        "synonyms": [
          "entrada",
          "pasaje"
        ],
        "examples": [
          "Compré el boleto por internet."
        ]
      }
    },
    "tags": [
      "noun",
      "travel"
    ],
    "level": "A1"
  },
  {
    "id": 13,
    "translations": {
      "en": {
        "text": "to",
        "phonetic": "/tuː/",
        "synonyms": [
          "toward",
          "with"
        ],
        "examples": [
          "We’re going to the park with friends."
        ]
      },
      "de": {
        "text": "zu",
        "phonetic": "/tsuː/",
        "synonyms": [
          "nach (Richtung)"
        ],
        "examples": [
          "Wir gehen zu meinen Freunden."
        ]
      },
      "es": {
        "text": "a",
        "phonetic": "/a/",
        "synonyms": [
          "hacia"
        ],
        "examples": [
          "Vamos a la plaza con Ana."
        ]
      }
    },
    "tags": [
      "preposition",
      "grammar"
    ],
    "level": "A1"
  },
  {
    "id": 14,
    "translations": {
      "en": {
        "text": "the money",
        "phonetic": "/ˈmʌni/",
        "synonyms": [
          "cash"
        ],
        "examples": [
          "I don’t have enough money today."
        ]
      },
      "de": {
        "text": "Das Geld",
        "phonetic": "/ɡɛlt/",
        "synonyms": [
          "Bargeld"
        ],
        "examples": [
          "Ich habe heute nicht genug Geld."
        ]
      },
      "es": {
        "text": "el dinero",
        "phonetic": "/diˈneɾo/",
        "synonyms": [
          "plata"
        ],
        "examples": [
          "No tengo suficiente dinero hoy."
        ]
      }
    },
    "tags": [
      "money",
      "object"
    ],
    "level": "A1"
  },
  {
    "id": 15,
    "translations": {
      "en": {
        "text": "where",
        "phonetic": "/wɛr/",
        "synonyms": [
          "in what place"
        ],
        "examples": [
          "Where are you from?"
        ]
      },
      "de": {
        "text": "wo",
        "phonetic": "/voː/",
        "synonyms": [
          "an welchem Ort"
        ],
        "examples": [
          "Wo kommst du her?"
        ]
      },
      "es": {
        "text": "dónde",
        "phonetic": "/ˈdonde/",
        "synonyms": [
          "en qué lugar"
        ],
        "examples": [
          "¿De dónde eres?"
        ]
      }
    },
    "tags": [
      "question",
      "adverb"
    ],
    "level": "A1"
  },
  {
    "id": 16,
    "translations": {
      "en": {
        "text": "the reservation",
        "phonetic": "/ˌrɛzərˈveɪʃən/",
        "synonyms": [
          "booking"
        ],
        "examples": [
          "I’d like to make a reservation for two."
        ]
      },
      "de": {
        "text": "Die Reservierung",
        "phonetic": "/ʁezɛʁˈviːʁʊŋ/",
        "synonyms": [
          "Buchung"
        ],
        "examples": [
          "Ich möchte eine Reservierung für zwei Personen machen."
        ]
      },
      "es": {
        "text": "la reserva",
        "phonetic": "/reˈseɾβa/",
        "synonyms": [
          "booking"
        ],
        "examples": [
          "Quisiera hacer una reserva para dos."
        ]
      }
    },
    "tags": [
      "travel",
      "noun"
    ],
    "level": "A1"
  },
  {
    "id": 17,
    "translations": {
      "en": {
        "text": "I've got",
        "phonetic": "/aɪv ɡɑːt/",
        "synonyms": [
          "I have"
        ],
        "examples": [
          "I’ve got a question, Is there a restroom here?"
        ]
      },
      "de": {
        "text": "ich habe",
        "phonetic": "/ɪç ˈhaːbə/",
        "synonyms": [
          "habe"
        ],
        "examples": [
          "Ich habe eine Frage, gibt es hier eine Toilette?"
        ]
      },
      "es": {
        "text": "tengo",
        "phonetic": "/ˈteŋɡo/",
        "synonyms": [
          "poseo"
        ],
        "examples": [
          "Tengo una pregunta: ¿hay un baño aquí?"
        ]
      }
    },
    "tags": [
      "verb",
      "have"
    ],
    "level": "A1"
  },
  {
    "id": 18,
    "translations": {
      "en": {
        "text": "it is",
        "phonetic": "/ɪt ɪz/",
        "synonyms": [
          "it’s"
        ],
        "examples": [
          "The Train is here."
        ]
      },
      "de": {
        "text": "es ist",
        "phonetic": "/ɛs ɪst/",
        "synonyms": [
          "ist"
        ],
        "examples": [
          "Der Zug ist da."
        ]
      },
      "es": {
        "text": "está",
        "phonetic": "/esˈta/",
        "synonyms": [
          "está"
        ],
        "examples": [
          "El tren está aquí."
        ]
      }
    },
    "tags": [
      "verb",
      "be"
    ],
    "level": "A1"
  },
  {
    "id": 19,
    "translations": {
      "en": {
        "text": "here",
        "phonetic": "/hɪr/",
        "synonyms": [
          "at this place"
        ],
        "examples": [
          "Please wait here."
        ]
      },
      "de": {
        "text": "hier",
        "phonetic": "/hiːɐ̯/",
        "synonyms": [
          "an diesem Ort"
        ],
        "examples": [
          "Bitte warte hier."
        ]
      },
      "es": {
        "text": "aquí",
        "phonetic": "/aˈki/",
        "synonyms": [
          "en este lugar"
        ],
        "examples": [
          "Espera aquí, por favor."
        ]
      }
    },
    "tags": [
      "place",
      "adverb"
    ],
    "level": "A1"
  },
  {
    "id": 20,
    "translations": {
      "en": {
        "text": "the hotel",
        "phonetic": "/hoʊˈtɛl/",
        "synonyms": [
          "inn"
        ],
        "examples": [
          "We’re staying at a small hotel near the station."
        ]
      },
      "de": {
        "text": "Das Hotel",
        "phonetic": "/hoˈtɛl/",
        "synonyms": [
          "Gasthaus"
        ],
        "examples": [
          "Wir übernachten in einem Hotel am Bahnhof."
        ]
      },
      "es": {
        "text": "el hotel",
        "phonetic": "/oˈtel/",
        "synonyms": [
          "hostal"
        ],
        "examples": [
          "Nos alojamos en un hotel cerca de la estación."
        ]
      }
    },
    "tags": [
      "place",
      "noun"
    ],
    "level": "A1"
  },
  {
    "id": 21,
    "translations": {
      "en": {
        "text": "in",
        "phonetic": "/ɪn/",
        "synonyms": [
          "inside"
        ],
        "examples": [
          "The keys are in my bag."
        ]
      },
      "de": {
        "text": "in",
        "phonetic": "/ɪn/",
        "synonyms": [
          "drin"
        ],
        "examples": [
          "Die Schlüssel sind in meiner Tasche."
        ]
      },
      "es": {
        "text": "en",
        "phonetic": "/en/",
        "synonyms": [
          "dentro de"
        ],
        "examples": [
          "Las llaves están en mi bolso."
        ]
      }
    },
    "tags": [
      "preposition",
      "grammar"
    ],
    "level": "A1"
  },
  {
    "id": 22,
    "translations": {
      "en": {
        "text": "the suitcase",
        "phonetic": "/ˈsuːtˌkeɪs/",
        "synonyms": [
          "luggage"
        ],
        "examples": [
          "My suitcase is too heavy."
        ]
      },
      "de": {
        "text": "Der Koffer",
        "phonetic": "/ˈkɔfɐ/",
        "synonyms": [
          "Reisekoffer"
        ],
        "examples": [
          "Mein Koffer ist zu schwer."
        ]
      },
      "es": {
        "text": "la maleta",
        "phonetic": "/maˈleta/",
        "synonyms": [
          "equipaje"
        ],
        "examples": [
          "Mi maleta pesa demasiado."
        ]
      }
    },
    "tags": [
      "noun",
      "travel"
    ],
    "level": "A1"
  },
  {
    "id": 23,
    "translations": {
      "en": {
        "text": "the passport",
        "phonetic": "/ˈpæspɔːrt/",
        "synonyms": [
          "travel document"
        ],
        "examples": [
          "Don’t forget your passport."
        ]
      },
      "de": {
        "text": "Der Pass",
        "phonetic": "/pas/",
        "synonyms": [
          "Reisepass"
        ],
        "examples": [
          "Vergiss deinen Pass nicht."
        ]
      },
      "es": {
        "text": "el pasaporte",
        "phonetic": "/pasaˈpoɾte/",
        "synonyms": [
          "documento de viaje"
        ],
        "examples": [
          "No olvides tu pasaporte."
        ]
      }
    },
    "tags": [
      "noun",
      "travel"
    ],
    "level": "A1"
  },
  {
    "id": 24,
    "translations": {
      "en": {
        "text": "my",
        "phonetic": "/maɪ/",
        "synonyms": [
          "mine (det.)"
        ],
        "examples": [
          "My brother lives in Berlin."
        ]
      },
      "de": {
        "text": "mein",
        "phonetic": "/maɪ̯n/",
        "synonyms": [
          "meine"
        ],
        "examples": [
          "Mein Bruder wohnt in Berlin."
        ]
      },
      "es": {
        "text": "mi",
        "phonetic": "/mi/",
        "synonyms": [
          "mío (adj.)"
        ],
        "examples": [
          "Mi hermano vive en Berlín."
        ]
      }
    },
    "tags": [
      "pronoun",
      "possessive",
      "grammar"
    ],
    "level": "A1"
  },
  {
    "id": 25,
    "translations": {
      "en": {
        "text": "the phone",
        "phonetic": "/foʊn/",
        "synonyms": [
          "telephone"
        ],
        "examples": [
          "I left my phone at home."
        ]
      },
      "de": {
        "text": "Das Telefon",
        "phonetic": "/ˈteːlefoːn/",
        "synonyms": [
          "Handy",
          "Telefonapparat"
        ],
        "examples": [
          "Ich habe mein Telefon zu Hause gelassen."
        ]
      },
      "es": {
        "text": "el teléfono",
        "phonetic": "/teˈlefono/",
        "synonyms": [
          "móvil",
          "celular"
        ],
        "examples": [
          "Dejé el teléfono en casa."
        ]
      }
    },
    "tags": [
      "noun",
      "technology"
    ],
    "level": "A1"
  },
  {
    "id": 26,
    "translations": {
      "en": {
        "text": "(I) need",
        "phonetic": "/aɪ niːd/",
        "synonyms": [
          "require"
        ],
        "examples": [
          "I need a ticket to Munich."
        ]
      },
      "de": {
        "text": "ich brauche",
        "phonetic": "/ɪç ˈbʁaʊ̯xə/",
        "synonyms": [
          "benötige"
        ],
        "examples": [
          "Ich brauche ein Ticket nach München."
        ]
      },
      "es": {
        "text": "necesito",
        "phonetic": "/neseˈsito/",
        "synonyms": [
          "requiero"
        ],
        "examples": [
          "Necesito un boleto a Múnich."
        ]
      }
    },
    "tags": [
      "verb",
      "need"
    ],
    "level": "A1"
  },
  {
    "id": 27,
    "translations": {
      "en": {
        "text": "the taxi",
        "phonetic": "/ˈtæksi/",
        "synonyms": [
          "cab"
        ],
        "examples": [
          "Let’s take a taxi to the hotel."
        ]
      },
      "de": {
        "text": "Das Taxi",
        "phonetic": "/ˈtaksi/",
        "synonyms": [
          "auto"
        ],
        "examples": [
          "Lass uns ein Taxi zum Hotel nehmen."
        ]
      },
      "es": {
        "text": "el taxi",
        "phonetic": "/ˈtaksi/",
        "synonyms": [
          "coche",
          "auto (de taxi)"
        ],
        "examples": [
          "Tomemos un taxi al hotel."
        ]
      }
    },
    "tags": [
      "transport",
      "noun"
    ],
    "level": "A1"
  },
  {
    "id": 28,
    "translations": {
      "en": {
        "text": "Spanish",
        "phonetic": "/ˈspænɪʃ/",
        "synonyms": [
          ""
        ],
        "examples": [
          "I speak a little Spanish."
        ]
      },
      "de": {
        "text": "Spanisch",
        "phonetic": "/ˈʃpaːnɪʃ/",
        "synonyms": [
          ""
        ],
        "examples": [
          "Ich spreche ein bisschen Spanisch."
        ]
      },
      "es": {
        "text": "español",
        "phonetic": "/espaˈɲol/",
        "synonyms": [
          ""
        ],
        "examples": [
          "Hablo un poco de español."
        ]
      }
    },
    "tags": [
      "language",
      "nationality"
    ],
    "level": "A1"
  },
  {
    "id": 29,
    "translations": {
      "en": {
        "text": "i speak",
        "phonetic": "/aɪ æm ˈtɔːkɪŋ/",
        "synonyms": [
          "say",
          "speak"
        ],
        "examples": [
          "I speak English at work."
        ]
      },
      "de": {
        "text": "ich spreche",
        "phonetic": "/ɪç ˈʃpʁɛçə/",
        "synonyms": [
          "rede"
        ],
        "examples": [
          "Ich spreche Deutsch und Englisch."
        ]
      },
      "es": {
        "text": "hablo",
        "phonetic": "/ˈaβlo/",
        "synonyms": [
          "converso"
        ],
        "examples": [
          "Hablo inglés en el trabajo."
        ]
      }
    },
    "tags": [
      "verb",
      "speak"
    ],
    "level": "A1"
  },
  {
    "id": 30,
    "translations": {
      "en": {
        "text": "(you) speak",
        "phonetic": "/duː juː spiːk/",
        "synonyms": [
          "can you speak"
        ],
        "examples": [
          "Do you speak German?"
        ]
      },
      "de": {
        "text": "du sprichst",
        "phonetic": "/duː ˈʃpʁɪçst/",
        "synonyms": [
          "kannst du sprechen"
        ],
        "examples": [
          "Sprichst du Deutsch?"
        ]
      },
      "es": {
        "text": "hablas",
        "phonetic": "/ˈaβlas/",
        "synonyms": [
          "puedes hablar"
        ],
        "examples": [
          "¿Hablas alemán?"
        ]
      }
    },
    "tags": [
      "verb",
      "speak"
    ],
    "level": "A1"
  },
  {
    "id": 31,
    "translations": {
      "en": {
        "text": "excuse me",
        "phonetic": "/ɪkˈskjuːz miː/",
        "synonyms": [
          "pardon me"
        ],
        "examples": [
          "Excuse me, where is the restroom?"
        ]
      },
      "de": {
        "text": "Entschuldigung",
        "phonetic": "/ɛntˈʃʊldɪɡʊŋ/",
        "synonyms": [
          "Verzeihung"
        ],
        "examples": [
          "Entschuldigung, wo ist die Toilette?"
        ]
      },
      "es": {
        "text": "disculpe",
        "phonetic": "/disˈkulpe/",
        "synonyms": [
          "perdón"
        ],
        "examples": [
          "Disculpe, ¿dónde está el baño?"
        ]
      }
    },
    "tags": [
      "politeness",
      "expression"
    ],
    "level": "A1"
  },
  {
    "id": 32,
    "translations": {
      "en": {
        "text": "English",
        "phonetic": "/ˈɪŋɡlɪʃ/",
        "synonyms": [
          ""
        ],
        "examples": [
          "Do you speak English?"
        ]
      },
      "de": {
        "text": "Englisch",
        "phonetic": "/ˈɛŋlɪʃ/",
        "synonyms": [
          ""
        ],
        "examples": [
          "Sprichst du Englisch?"
        ]
      },
      "es": {
        "text": "inglés",
        "phonetic": "/iŋˈɡles/",
        "synonyms": [
          ""
        ],
        "examples": [
          "¿Hablas inglés?"
        ]
      }
    },
    "tags": [
      "language",
      "nationality"
    ],
    "level": "A1"
  },
  {
    "id": 33,
    "translations": {
      "en": {
        "text": "do not",
        "phonetic": "/duː nɑːt/",
        "synonyms": [
          "don’t"
        ],
        "examples": [
          "I do not understand."
        ]
      },
      "de": {
        "text": "nicht",
        "phonetic": "/nɪçt/",
        "synonyms": [
          "kein (neg.)"
        ],
        "examples": [
          "Ich verstehe nicht."
        ]
      },
      "es": {
        "text": "no",
        "phonetic": "/no/",
        "synonyms": [
          "en absoluto"
        ],
        "examples": [
          "No entiendo."
        ]
      }
    },
    "tags": [
      "negation",
      "grammar"
    ],
    "level": "A1"
  },
  {
    "id": 34,
    "translations": {
      "en": {
        "text": "yes",
        "phonetic": "/jɛs/",
        "synonyms": [
          "yeah"
        ],
        "examples": [
          "Yes, I’d love some coffee."
        ]
      },
      "de": {
        "text": "ja",
        "phonetic": "/jaː/",
        "synonyms": [
          "jawohl"
        ],
        "examples": [
          "Ja, gerne."
        ]
      },
      "es": {
        "text": "sí",
        "phonetic": "/si/",
        "synonyms": [
          "claro"
        ],
        "examples": [
          "Sí, me encantaría."
        ]
      }
    },
    "tags": [
      "answer",
      "grammar"
    ],
    "level": "A1"
  },
  {
    "id": 35,
    "translations": {
      "en": {
        "text": "please",
        "phonetic": "/pliːz/",
        "synonyms": [
          "kindly"
        ],
        "examples": [
          "A table for two, please."
        ]
      },
      "de": {
        "text": "bitte",
        "phonetic": "/ˈbɪtə/",
        "synonyms": [
          "freundlicherweise"
        ],
        "examples": [
          "Ein Tisch für zwei, bitte."
        ]
      },
      "es": {
        "text": "por favor",
        "phonetic": "/poɾ faˈβoɾ/",
        "synonyms": [
          "desculpe"
        ],
        "examples": [
          "Una mesa para dos, por favor."
        ]
      }
    },
    "tags": [
      "politeness",
      "expression"
    ],
    "level": "A1"
  },
  {
    "id": 36,
    "translations": {
      "en": {
        "text": "you're welcome",
        "phonetic": "/jʊr ˈwɛlkəm/",
        "synonyms": [
          "no problem"
        ],
        "examples": [
          "—Thanks! —You’re welcome."
        ]
      },
      "de": {
        "text": "gern geschehen",
        "phonetic": "/ˈɡɛʁn ɡəˈʃeːən/",
        "synonyms": [
          "keine Ursache"
        ],
        "examples": [
          "—Danke! —Gern geschehen."
        ]
      },
      "es": {
        "text": "de nada",
        "phonetic": "/de ˈnaða/",
        "synonyms": [
          "no hay de qué"
        ],
        "examples": [
          "—¡Gracias! —De nada."
        ]
      }
    },
    "tags": [
      "politeness",
      "expression"
    ],
    "level": "A1"
  },
  {
    "id": 37,
    "translations": {
      "en": {
        "text": "pardon",
        "phonetic": "/ˈsɔːri/",
        "synonyms": [
          "sorry",
          "excuse me"
        ],
        "examples": [
          "Sorry, I didn’t see you."
        ]
      },
      "de": {
        "text": "es tut mir leid",
        "phonetic": "/ɛs tuːt miːɐ̯ laɪ̯t/",
        "synonyms": [
          "Entschuldigung"
        ],
        "examples": [
          "Es tut mir leid, ich habe dich nicht gesehen."
        ]
      },
      "es": {
        "text": "perdón",
        "phonetic": "/peɾˈðon/",
        "synonyms": [
          "disculpa"
        ],
        "examples": [
          "Perdón, no te vi."
        ]
      }
    },
    "tags": [
      "apology",
      "politeness"
    ],
    "level": "A1"
  },
  {
    "id": 38,
    "translations": {
      "en": {
        "text": "sorry",
        "phonetic": "/ˈsɔːri/",
        "synonyms": [
          "my apologies",
          "I am sorry"
        ],
        "examples": [
          "I’m sorry for the delay."
        ]
      },
      "de": {
        "text": "es tut mir leid",
        "phonetic": "/ɛs tuːt miːɐ̯ laɪ̯t/",
        "synonyms": [
          "Verzeihung"
        ],
        "examples": [
          "Es tut mir leid wegen der Verspätung."
        ]
      },
      "es": {
        "text": "lo siento",
        "phonetic": "/lo ˈsjento/",
        "synonyms": [
          "perdón"
        ],
        "examples": [
          "Lo siento por el retraso."
        ]
      }
    },
    "tags": [
      "apology",
      "politeness"
    ],
    "level": "A1"
  },
  {
    "id": 39,
    "translations": {
      "en": {
        "text": "goodbye",
        "phonetic": "/ˌɡʊdˈbaɪ/",
        "synonyms": [
          "bye"
        ],
        "examples": [
          "Goodbye! See you tomorrow."
        ]
      },
      "de": {
        "text": "Auf Wiedersehen",
        "phonetic": "/aʊ̯f ˈviːdɐˌzeːən/",
        "synonyms": [
          "tschüss"
        ],
        "examples": [
          "Auf Wiedersehen! Bis morgen."
        ]
      },
      "es": {
        "text": "adiós",
        "phonetic": "/aˈðjos/",
        "synonyms": [
          "hasta luego"
        ],
        "examples": [
          "¡Adiós! Hasta mañana."
        ]
      }
    },
    "tags": [
      "farewell",
      "expression"
    ],
    "level": "A1"
  },
  {
    "id": 40,
    "translations": {
      "en": {
        "text": "nice to meet you",
        "phonetic": "/naɪs tə ˈmiːt juː/",
        "synonyms": [
          "pleased to meet you"
        ],
        "examples": [
          "Nice to meet you, Maria."
        ]
      },
      "de": {
        "text": "Freut mich dich kennenzulernen",
        "phonetic": "/fʁɔʏ̯t mɪç .../",
        "synonyms": [
          "angenehm"
        ],
        "examples": [
          "Freut mich, Maria kennenzulernen."
        ]
      },
      "es": {
        "text": "mucho gusto",
        "phonetic": "/ˈmutʃo ˈɣusto/",
        "synonyms": [
          "encantado"
        ],
        "examples": [
          "Mucho gusto, María."
        ]
      }
    },
    "tags": [
      "greeting",
      "expression"
    ],
    "level": "A1"
  },
  {
    "id": 41,
    "translations": {
      "en": {
        "text": "good morning",
        "phonetic": "/ɡʊd ˈmɔːrnɪŋ/",
        "synonyms": [
          "morning"
        ],
        "examples": [
          "Good morning! How did you sleep?"
        ]
      },
      "de": {
        "text": "Guten Morgen",
        "phonetic": "/ˈɡuːtn̩ ˈmɔʁɡn̩/",
        "synonyms": [
          "Morgen!"
        ],
        "examples": [
          "Guten Morgen! Wie hast du geschlafen?"
        ]
      },
      "es": {
        "text": "buenos días",
        "phonetic": "/ˈbwenos ˈdi.as/",
        "synonyms": [
          "¡Buen día!"
        ],
        "examples": [
          "¡Buenos días! ¿Cómo dormiste?"
        ]
      }
    },
    "tags": [
      "greeting",
      "time"
    ],
    "level": "A1"
  },
  {
    "id": 42,
    "translations": {
      "en": {
        "text": "thanks",
        "phonetic": "/θæŋks/",
        "synonyms": [
          "cheers"
        ],
        "examples": [
          "Thanks for your help!"
        ]
      },
      "de": {
        "text": "danke",
        "phonetic": "/ˈdaŋkə/",
        "synonyms": [
          "vielen Dank"
        ],
        "examples": [
          "Danke für deine Hilfe!"
        ]
      },
      "es": {
        "text": "gracias",
        "phonetic": "/ˈɡɾasjas/",
        "synonyms": [
          "muchas gracias"
        ],
        "examples": [
          "¡Gracias por tu ayuda!"
        ]
      }
    },
    "tags": [
      "thanks",
      "politeness"
    ],
    "level": "A1"
  },
  {
    "id": 43,
    "translations": {
      "en": {
        "text": "hello",
        "phonetic": "/həˈloʊ; haɪ/",
        "synonyms": [
          "hey",
          "hi"
        ],
        "examples": [
          "Hello! How are you?"
        ]
      },
      "de": {
        "text": "hallo",
        "phonetic": "/haˈloː/",
        "synonyms": [
          "hi"
        ],
        "examples": [
          "Hallo! Wie geht’s?"
        ]
      },
      "es": {
        "text": "hola",
        "phonetic": "/ˈola/",
        "synonyms": [
          "¡buenas!"
        ],
        "examples": [
          "¡Hola! ¿Cómo estás?"
        ]
      }
    },
    "tags": [
      "greeting",
      "basic"
    ],
    "level": "A1"
  },
  {
    "id": 44,
    "translations": {
      "en": {
        "text": "good night",
        "phonetic": "/ɡʊd naɪt/",
        "synonyms": [
          "night-night"
        ],
        "examples": [
          "Good night! See you tomorrow."
        ]
      },
      "de": {
        "text": "Gute Nacht",
        "phonetic": "/ˈɡuːtə naxt/",
        "synonyms": [
          "schlaf gut"
        ],
        "examples": [
          "Gute Nacht! Bis morgen."
        ]
      },
      "es": {
        "text": "buenas noches",
        "phonetic": "/ˈbwenas ˈnotʃes/",
        "synonyms": [
          "que descanses"
        ],
        "examples": [
          "Buenas noches, hasta mañana."
        ]
      }
    },
    "tags": [
      "greeting",
      "time"
    ],
    "level": "A1"
  },
  {
    "id": 45,
    "translations": {
      "en": {
        "text": "(you) drink",
        "phonetic": "/juː drɪŋk/",
        "synonyms": [
          "have (a drink)"
        ],
        "examples": [
          "Do you drink coffee in the morning?"
        ]
      },
      "de": {
        "text": "du trinkst",
        "phonetic": "/duː tʁɪŋkst/",
        "synonyms": [
          "trinkst du"
        ],
        "examples": [
          "Trinkst du morgens Kaffee?"
        ]
      },
      "es": {
        "text": "bebes",
        "phonetic": "/ˈβeβes/",
        "synonyms": [
          "tomas"
        ],
        "examples": [
          "¿Bebes café por la mañana?"
        ]
      }
    },
    "tags": [
      "verb",
      "drink"
    ],
    "level": "A1"
  },
  {
    "id": 46,
    "translations": {
      "en": {
        "text": "the water",
        "phonetic": "/ˈwɔːtər/",
        "synonyms": [
          "H2O"
        ],
        "examples": [
          "I drink a lot of water."
        ]
      },
      "de": {
        "text": "Das Wasser",
        "phonetic": "/ˈvasɐ/",
        "synonyms": [
          "Trinkwasser"
        ],
        "examples": [
          "Ich trinke viel Wasser."
        ]
      },
      "es": {
        "text": "el agua",
        "phonetic": "/ˈaɣwa/",
        "synonyms": [
          "agua potable"
        ],
        "examples": [
          "Bebo mucha agua."
        ]
      }
    },
    "tags": [
      "drink",
      "food",
      "noun"
    ],
    "level": "A1"
  },
  {
    "id": 47,
    "translations": {
      "en": {
        "text": "(I) eat",
        "phonetic": "/aɪ iːt/",
        "synonyms": [
          "have (food)"
        ],
        "examples": [
          "I eat breakfast at seven."
        ]
      },
      "de": {
        "text": "ich esse",
        "phonetic": "/ɪç ˈʔɛsə/",
        "synonyms": [
          "esse"
        ],
        "examples": [
          "Ich esse um sieben Uhr Frühstück."
        ]
      },
      "es": {
        "text": "como",
        "phonetic": "/ˈkomo/",
        "synonyms": [
          "ingiero"
        ],
        "examples": [
          "Como el desayuno a las siete."
        ]
      }
    },
    "tags": [
      "verb",
      "eat"
    ],
    "level": "A1"
  },
  {
    "id": 48,
    "translations": {
      "en": {
        "text": "(I) drink",
        "phonetic": "/aɪ drɪŋk/",
        "synonyms": [
          "have (a beverage)"
        ],
        "examples": [
          "I drink tea in the afternoon."
        ]
      },
      "de": {
        "text": "ich trinke",
        "phonetic": "/ɪç ˈtʁɪŋkə/",
        "synonyms": [
          "trinke"
        ],
        "examples": [
          "Ich trinke nachmittags Tee."
        ]
      },
      "es": {
        "text": "bebo",
        "phonetic": "/ˈβeβo/",
        "synonyms": [
          "tomo"
        ],
        "examples": [
          "Bebo té por la tarde."
        ]
      }
    },
    "tags": [
      "verb",
      "drink"
    ],
    "level": "A1"
  },
  {
    "id": 49,
    "translations": {
      "en": {
        "text": "the milk",
        "phonetic": "/mɪlk/",
        "synonyms": [
          "dairy milk"
        ],
        "examples": [
          "She drinks milk with cereal."
        ]
      },
      "de": {
        "text": "Die Milch",
        "phonetic": "/mɪlç/",
        "synonyms": [
          "Kuhmilch"
        ],
        "examples": [
          "Sie trinkt Milch zum Müsli."
        ]
      },
      "es": {
        "text": "la leche",
        "phonetic": "/ˈletʃe/",
        "synonyms": [
          "leche de vaca"
        ],
        "examples": [
          "Ella bebe leche con cereales."
        ]
      }
    },
    "tags": [
      "drink",
      "food"
    ],
    "level": "A1"
  },
  {
    "id": 50,
    "translations": {
      "en": {
        "text": "the bread",
        "phonetic": "/brɛd/",
        "synonyms": [
          "loaf"
        ],
        "examples": [
          "We bought fresh bread this morning."
        ]
      },
      "de": {
        "text": "Das Brot",
        "phonetic": "/bʁoːt/",
        "synonyms": [
          "Laib"
        ],
        "examples": [
          "Wir haben heute Morgen frisches Brot gekauft."
        ]
      },
      "es": {
        "text": "el pan",
        "phonetic": "/pan/",
        "synonyms": [
          "hogaza"
        ],
        "examples": [
          "Compramos pan fresco esta mañana."
        ]
      }
    },
    "tags": [
      "food"
    ],
    "level": "A1"
  },
  {
    "id": 51,
    "translations": {
      "en": {
        "text": "(he) drinks",
        "phonetic": "/hiː drɪŋks/",
        "synonyms": [
          "is having a drink"
        ],
        "examples": [
          "He drinks water."
        ]
      },
      "de": {
        "text": "er trinkt",
        "phonetic": "/eːɐ̯ tʁɪŋkt/",
        "synonyms": [
          "trinkt"
        ],
        "examples": [
          "Er trinkt gerade Wasser."
        ]
      },
      "es": {
        "text": "bebe",
        "phonetic": "/ˈβeβe/",
        "synonyms": [
          "toma"
        ],
        "examples": [
          "Él bebe agua ahora."
        ]
      }
    },
    "tags": [
      "verb",
      "drink"
    ],
    "level": "A1"
  },
  {
    "id": 52,
    "translations": {
      "en": {
        "text": "you eat",
        "phonetic": "/eɪt/",
        "synonyms": [
          "consume"
        ],
        "examples": [
          "Do you eat meat?"
        ]
      },
      "de": {
        "text": "du isst",
        "phonetic": "/duː ɪst/",
        "synonyms": [
          "isst du"
        ],
        "examples": [
          "Isst du Fleisch?"
        ]
      },
      "es": {
        "text": "comes",
        "phonetic": "/ˈkomes/",
        "synonyms": [
          "ingieres"
        ],
        "examples": [
          "¿Comes carne?"
        ]
      }
    },
    "tags": [
      "verb",
      "eat"
    ],
    "level": "A1"
  },
  {
    "id": 53,
    "translations": {
      "en": {
        "text": "(it) is",
        "phonetic": "/ɪz/",
        "synonyms": [
          "be"
        ],
        "examples": [
          "The picture is pretty."
        ]
      },
      "de": {
        "text": "(Es) ist",
        "phonetic": "/ɪst/",
        "synonyms": [
          "sein"
        ],
        "examples": [
          "Das Bild ist hübsch"
        ]
      },
      "es": {
        "text": "es",
        "phonetic": "/es/",
        "synonyms": [
          "ser (3. Sg.)"
        ],
        "examples": [
          "La imagen es bonita.?"
        ]
      }
    },
    "tags": [
      "verb",
      "be"
    ],
    "level": "A1"
  },
  {
    "id": 54,
    "translations": {
      "en": {
        "text": "she, her",
        "phonetic": "/ʃiː; hɜːr/",
        "synonyms": [
          "female pronoun"
        ],
        "examples": [
          "She is my sister."
        ]
      },
      "de": {
        "text": "sie",
        "phonetic": "/ziː/",
        "synonyms": [
          "weibliches Pronomen"
        ],
        "examples": [
          "Sie ist meine Schwester."
        ]
      },
      "es": {
        "text": "ella",
        "phonetic": "/ˈeʝa/",
        "synonyms": [
          "pronombre femenino"
        ],
        "examples": [
          "Ella es mi hermana."
        ]
      }
    },
    "tags": [
      "pronoun",
      "person"
    ],
    "level": "A1"
  },
  {
    "id": 55,
    "translations": {
      "en": {
        "text": "you are",
        "phonetic": "/jʊr; ɑːr/",
        "synonyms": [
          "be"
        ],
        "examples": [
          "You’re very kind."
        ]
      },
      "de": {
        "text": "du bist",
        "phonetic": "/duː bɪst/",
        "synonyms": [
          "bist du"
        ],
        "examples": [
          "Du bist sehr nett."
        ]
      },
      "es": {
        "text": "eres",
        "phonetic": "/ˈeɾes/",
        "synonyms": [
          "tú eres"
        ],
        "examples": [
          "Eres muy amable."
        ]
      }
    },
    "tags": [
      "verb",
      "be"
    ],
    "level": "A1"
  },
  {
    "id": 56,
    "translations": {
      "en": {
        "text": "he, him",
        "phonetic": "/hiː; hɪm/",
        "synonyms": [
          "male pronoun"
        ],
        "examples": [
          "He is my friend."
        ]
      },
      "de": {
        "text": "er",
        "phonetic": "/eːɐ̯/",
        "synonyms": [
          "männliches Pronomen"
        ],
        "examples": [
          "Er ist mein Freund."
        ]
      },
      "es": {
        "text": "él",
        "phonetic": "/el/",
        "synonyms": [
          "él (pronombre)"
        ],
        "examples": [
          "Él es mi amigo."
        ]
      }
    },
    "tags": [
      "pronoun",
      "grammar"
    ],
    "level": "A1"
  },
  {
    "id": 57,
    "translations": {
      "en": {
        "text": "you",
        "phonetic": "/juː/",
        "synonyms": [
          "second-person pronoun"
        ],
        "examples": [
          "You are welcome to join us."
        ]
      },
      "de": {
        "text": "du",
        "phonetic": "/duː/",
        "synonyms": [
          "zweite Person Singular"
        ],
        "examples": [
          "Du kannst gern mitkommen."
        ]
      },
      "es": {
        "text": "tú",
        "phonetic": "/tu/",
        "synonyms": [
          "tú (pronombre)"
        ],
        "examples": [
          "Tú puedes venir con nosotros."
        ]
      }
    },
    "tags": [
      "pronoun",
      "person"
    ],
    "level": "A1"
  },
  {
    "id": 58,
    "translations": {
      "en": {
        "text": "(she) eats",
        "phonetic": "/ʃiː iːts/",
        "synonyms": [
          "consumes"
        ],
        "examples": [
          "She eats fruit every day."
        ]
      },
      "de": {
        "text": "sie isst",
        "phonetic": "/ziː ɪst/",
        "synonyms": [
          "isst"
        ],
        "examples": [
          "Sie isst jeden Tag Obst."
        ]
      },
      "es": {
        "text": "come",
        "phonetic": "/ˈkome/",
        "synonyms": [
          "ingiere"
        ],
        "examples": [
          "Ella come fruta todos los días."
        ]
      }
    },
    "tags": [
      "verb",
      "eat"
    ],
    "level": "A1"
  },
  {
    "id": 59,
    "translations": {
      "en": {
        "text": "apple",
        "phonetic": "/ˈæpəl/",
        "synonyms": [
          "fruit"
        ],
        "examples": [
          "I eat an apple every afternoon."
        ]
      },
      "de": {
        "text": "Apfel",
        "phonetic": "/ˈapfəl/",
        "synonyms": [
          "Obst"
        ],
        "examples": [
          "Ich esse jeden Nachmittag einen Apfel."
        ]
      },
      "es": {
        "text": "manzana",
        "phonetic": "/manˈsana/",
        "synonyms": [
          "fruta"
        ],
        "examples": [
          "Como una manzana cada tarde."
        ]
      }
    },
    "tags": [
      "food",
      "fruit"
    ],
    "level": "A1"
  },
  {
    "id": 60,
    "translations": {
      "en": {
        "text": "I am, am",
        "phonetic": "/aɪ æm/",
        "synonyms": [
          "I’m"
        ],
        "examples": [
          "I am from Germany."
        ]
      },
      "de": {
        "text": "ich bin",
        "phonetic": "/ɪç bɪn/",
        "synonyms": [
          "bin"
        ],
        "examples": [
          "Ich bin aus Deutschland."
        ]
      },
      "es": {
        "text": "soy",
        "phonetic": "/soj/",
        "synonyms": [
          "yo soy"
        ],
        "examples": [
          "Soy de Alemania."
        ]
      }
    },
    "tags": [
      "verb",
      "be"
    ],
    "level": "A1"
  },
  {
    "id": 61,
    "translations": {
      "en": {
        "text": "the boy",
        "phonetic": "/bɔɪ/",
        "synonyms": [
          "child",
          "kid"
        ],
        "examples": [
          "The boy is playing in the park."
        ]
      },
      "de": {
        "text": "Der Junge",
        "phonetic": "/ˈjʊŋə/",
        "synonyms": [
          "Bub"
        ],
        "examples": [
          "Der Junge spielt im Park."
        ]
      },
      "es": {
        "text": "el niño",
        "phonetic": "/ˈniɲo/",
        "synonyms": [
          "chico"
        ],
        "examples": [
          "El niño juega en el parque."
        ]
      }
    },
    "tags": [
      "person",
      "child"
    ],
    "level": "A1"
  },
  {
    "id": 62,
    "translations": {
      "en": {
        "text": "the man",
        "phonetic": "/mæn/",
        "synonyms": [
          "male",
          "gentleman"
        ],
        "examples": [
          "The man is waiting at the door."
        ]
      },
      "de": {
        "text": "Der Mann",
        "phonetic": "/man/",
        "synonyms": [
          "Herr"
        ],
        "examples": [
          "Der Mann wartet an der Tür."
        ]
      },
      "es": {
        "text": "el hombre",
        "phonetic": "/ˈombɾe/",
        "synonyms": [
          "señor"
        ],
        "examples": [
          "El hombre espera en la puerta."
        ]
      }
    },
    "tags": [
      "person",
      "adult"
    ],
    "level": "A1"
  },
  {
    "id": 63,
    "translations": {
      "en": {
        "text": "a, an (fem.)",
        "phonetic": "/ə; æn; wʌn/",
        "synonyms": [
          ""
        ],
        "examples": [
          "I’d like a coffee, please."
        ]
      },
      "de": {
        "text": "eine (fem.)",
        "phonetic": "/ˈaɪ̯nə/",
        "synonyms": [
          ""
        ],
        "examples": [
          "Ich hätte gerne eine Tasse Kaffee."
        ]
      },
      "es": {
        "text": "una (fem.)",
        "phonetic": "/ˈuna/",
        "synonyms": [
          ""
        ],
        "examples": [
          "Quiero una taza de café."
        ]
      }
    },
    "tags": [
      "article",
      "grammar"
    ],
    "level": "A1"
  },
  {
    "id": 64,
    "translations": {
      "en": {
        "text": "I, me",
        "phonetic": "/aɪ; miː/",
        "synonyms": [
          ""
        ],
        "examples": [
          "I am learning German."
        ]
      },
      "de": {
        "text": "ich",
        "phonetic": "/ɪç/",
        "synonyms": [
          ""
        ],
        "examples": [
          "Ich lerne Deutsch."
        ]
      },
      "es": {
        "text": "yo",
        "phonetic": "/jo/",
        "synonyms": [
          ""
        ],
        "examples": [
          "Yo estudio alemán."
        ]
      }
    },
    "tags": [
      "pronoun",
      "person"
    ],
    "level": "A1"
  },
  {
    "id": 65,
    "translations": {
      "en": {
        "text": "the (fem.)",
        "phonetic": "/ðə; ðiː/",
        "synonyms": [
          ""
        ],
        "examples": [
          "The museum opens at ten."
        ]
      },
      "de": {
        "text": "die (fem.)",
        "phonetic": "/diː/",
        "synonyms": [
          ""
        ],
        "examples": [
          "Die Bibliothek öffnet um zehn."
        ]
      },
      "es": {
        "text": "la (fem.)",
        "phonetic": "/la/",
        "synonyms": [
          ""
        ],
        "examples": [
          "La biblioteca abre a las diez."
        ]
      }
    },
    "tags": [
      "article",
      "grammar"
    ],
    "level": "A1"
  },
  {
    "id": 66,
    "translations": {
      "en": {
        "text": "the girl",
        "phonetic": "/ɡɜːrl/",
        "synonyms": [
          "child",
          "daughter"
        ],
        "examples": [
          "The girl is reading a book."
        ]
      },
      "de": {
        "text": "Das Mädchen",
        "phonetic": "/ˈmɛːtçən/",
        "synonyms": [
          "Mädchen",
          "Tochter"
        ],
        "examples": [
          "Das Mädchen liest ein Buch."
        ]
      },
      "es": {
        "text": "la niña",
        "phonetic": "/ˈniɲa/",
        "synonyms": [
          "chica",
          "hija"
        ],
        "examples": [
          "La niña lee un libro."
        ]
      }
    },
    "tags": [
      "person",
      "child"
    ],
    "level": "A1"
  },
  {
    "id": 67,
    "translations": {
      "en": {
        "text": "a, an (masc.)",
        "phonetic": "/ə; æn/",
        "synonyms": [
          ""
        ],
        "examples": [
          "I saw a cat in the garden."
        ]
      },
      "de": {
        "text": "ein (mask.)",
        "phonetic": "/aɪ̯n/",
        "synonyms": [
          ""
        ],
        "examples": [
          "Ich habe einen Hund gesehen."
        ]
      },
      "es": {
        "text": "un (masc.)",
        "phonetic": "/un/",
        "synonyms": [
          ""
        ],
        "examples": [
          "Vi un gato en el jardín."
        ]
      }
    },
    "tags": [
      "article",
      "grammar"
    ],
    "level": "A1"
  },
  {
    "id": 68,
    "translations": {
      "en": {
        "text": "the (masc.)",
        "phonetic": "/ðə; ðiː/",
        "synonyms": [
          "article (masc.)"
        ],
        "examples": [
          "The train leaves at nine."
        ]
      },
      "de": {
        "text": "der (mask.)",
        "phonetic": "/deːɐ̯/",
        "synonyms": [
          ""
        ],
        "examples": [
          "Der Zug fährt um neun Uhr ab."
        ]
      },
      "es": {
        "text": "el (masc.)",
        "phonetic": "/el/",
        "synonyms": [
          ""
        ],
        "examples": [
          "El tren sale a las nueve."
        ]
      }
    },
    "tags": [
      "article",
      "grammar"
    ],
    "level": "A1"
  },
  {
    "id": 69,
    "translations": {
      "en": {
        "text": "the woman",
        "phonetic": "/ˈwʊmən/",
        "synonyms": [
          "female",
          "lady"
        ],
        "examples": [
          "The woman is talking on the phone."
        ]
      },
      "de": {
        "text": "Die Frau",
        "phonetic": "/fʁaʊ̯/",
        "synonyms": [
          "Dame"
        ],
        "examples": [
          "Die Frau telefoniert."
        ]
      },
      "es": {
        "text": "la mujer",
        "phonetic": "/muˈxeɾ/",
        "synonyms": [
          "señora"
        ],
        "examples": [
          "La mujer está hablando por teléfono."
        ]
      }
    },
    "tags": [
      "person",
      "adult"
    ],
    "level": "A1"
  },
  {
    "id": 70,
    "translations": {
      "en": {
        "text": "two",
        "phonetic": "tuː",
        "synonyms": null,
        "examples": [
          "two apples"
        ]
      },
      "de": {
        "text": "zwei",
        "phonetic": "tsvaɪ̯",
        "synonyms": null,
        "examples": [
          "zwei Äpfel"
        ]
      },
      "es": {
        "text": "dos",
        "phonetic": "dos",
        "synonyms": null,
        "examples": [
          "dos manzanas"
        ]
      }
    },
    "tags": [
      "number",
      "basic"
    ],
    "level": "A1"
  },
  {
    "id": 71,
    "translations": {
      "en": {
        "text": "for",
        "phonetic": "fɔːr",
        "synonyms": null,
        "examples": [
          "A table for two, please"
        ]
      },
      "de": {
        "text": "für",
        "phonetic": "fyːɐ̯",
        "synonyms": null,
        "examples": [
          "Ein Tisch für zwei, bitte"
        ]
      },
      "es": {
        "text": "para",
        "phonetic": "ˈpaɾa",
        "synonyms": null,
        "examples": [
          "Una mesa para dos, por favor"
        ]
      }
    },
    "tags": [
      "basic",
      "preposition"
    ],
    "level": "A1"
  },
  {
    "id": 72,
    "translations": {
      "en": {
        "text": "The people",
        "phonetic": "ðə ˈpiːpəl",
        "synonyms": [
          "humans"
        ],
        "examples": [
          "Many people learn English as a second language."
        ]
      },
      "de": {
        "text": "Die Leute",
        "phonetic": "diː ˈlɔʏ̯tə",
        "synonyms": [
          "Menschen"
        ],
        "examples": [
          "Viele Menschen lernen Englisch als Zweitsprache."
        ]
      },
      "es": {
        "text": "Las personas",
        "phonetic": "las peɾˈsonas",
        "synonyms": [
          "gente"
        ],
        "examples": [
          "Muchas personas aprenden inglés como segundo idioma."
        ]
      }
    },
    "tags": [
      "noun",
      "people"
    ],
    "level": "A1"
  },
  {
    "id": 73,
    "translations": {
      "en": {
        "text": "The table",
        "phonetic": "ðə ˈteɪbəl",
        "synonyms": null,
        "examples": [
          "Dinner will be served at the table."
        ]
      },
      "de": {
        "text": "Der Tisch",
        "phonetic": "deːɐ̯ tɪʃ",
        "synonyms": null,
        "examples": [
          "Das Abendessen wird am Tisch serviert."
        ]
      },
      "es": {
        "text": "La mesa",
        "phonetic": "la ˈmesa",
        "synonyms": null,
        "examples": [
          "La cena se servirá en la mesa."
        ]
      }
    },
    "tags": [
      "noun",
      "furniture"
    ],
    "level": "A1"
  },
  {
    "id": 74,
    "translations": {
      "en": {
        "text": "The restaurant",
        "phonetic": "ðə ˈrɛst(ə)rɒnt",
        "synonyms": [
          "diner",
          "cafe"
        ],
        "examples": [
          "I am eating at a restaurant."
        ]
      },
      "de": {
        "text": "Das Restaurant",
        "phonetic": "das ʁɛstoˈʁɑ̃ː",
        "synonyms": [
          "Lokal",
          "Gaststätte"
        ],
        "examples": [
          "Ich esse in einem Restaurant."
        ]
      },
      "es": {
        "text": "El restaurante",
        "phonetic": "el restauˈɾante",
        "synonyms": [
          "bar"
        ],
        "examples": [
          "Yo como en un restaurante."
        ]
      }
    },
    "tags": [
      "noun",
      "food",
      "places"
    ],
    "level": "A1"
  },
  {
    "id": 75,
    "translations": {
      "en": {
        "text": "one",
        "phonetic": "wʌn",
        "synonyms": null,
        "examples": [
          "The children count from one to ten."
        ]
      },
      "de": {
        "text": "eins",
        "phonetic": "aɪ̯ns",
        "synonyms": null,
        "examples": [
          "Die Kinder zählen von eins bis zehn."
        ]
      },
      "es": {
        "text": "uno",
        "phonetic": "ˈuno",
        "synonyms": null,
        "examples": [
          "Los niños cuentan del uno al diez."
        ]
      }
    },
    "tags": [
      "number",
      "basic"
    ],
    "level": "A1"
  },
  {
    "id": 76,
    "translations": {
      "en": {
        "text": "three",
        "phonetic": "θriː",
        "synonyms": null,
        "examples": [
          "three bananas"
        ]
      },
      "de": {
        "text": "drei",
        "phonetic": "dʁaɪ̯",
        "synonyms": null,
        "examples": [
          "Drei Bananen"
        ]
      },
      "es": {
        "text": "tres",
        "phonetic": "tɾes",
        "synonyms": null,
        "examples": [
          "tres plátanos"
        ]
      }
    },
    "tags": [
      "number",
      "basic"
    ],
    "level": "A1"
  },
  {
    "id": 77,
    "translations": {
      "en": {
        "text": "The meat",
        "phonetic": "ðə miːt",
        "synonyms": [
          "pork",
          "beef"
        ],
        "examples": [
          "I like meat"
        ]
      },
      "de": {
        "text": "Das Fleisch",
        "phonetic": "das flaɪ̯ʃ",
        "synonyms": [
          ""
        ],
        "examples": [
          "Ich mag Fleisch"
        ]
      },
      "es": {
        "text": "La carne",
        "phonetic": "la ˈkaɾne",
        "synonyms": [
          ""
        ],
        "examples": [
          "Me gusta la carne."
        ]
      }
    },
    "tags": [
      "noun",
      "food"
    ],
    "level": "A1"
  },
  {
    "id": 78,
    "translations": {
      "en": {
        "text": "the cheese",
        "phonetic": "ðə tʃiːz",
        "synonyms": [
          ""
        ],
        "examples": [
          "A cheese sandwich"
        ]
      },
      "de": {
        "text": "Der Käse",
        "phonetic": "deːɐ̯ ˈkɛːzə",
        "synonyms": [
          ""
        ],
        "examples": [
          "Ein Käsebrot."
        ]
      },
      "es": {
        "text": "el queso",
        "phonetic": "el ˈkeso",
        "synonyms": [
          ""
        ],
        "examples": [
          "Un pan de queso."
        ]
      }
    },
    "tags": [
      "noun",
      "food"
    ],
    "level": "A1"
  },
  {
    "id": 79,
    "translations": {
      "en": {
        "text": "the fish",
        "phonetic": "ðə fɪʃ",
        "synonyms": [
          ""
        ],
        "examples": [
          "Sushi is rice with fish."
        ]
      },
      "de": {
        "text": "Der Fisch",
        "phonetic": "deːɐ̯ fɪʃ",
        "synonyms": [
          ""
        ],
        "examples": [
          "Sushi ist Reis mit Fisch."
        ]
      },
      "es": {
        "text": "el pescado",
        "phonetic": "el pesˈkaðo",
        "synonyms": [
          ""
        ],
        "examples": [
          "El sushi es arroz con pescado."
        ]
      }
    },
    "tags": [
      "noun",
      "animal"
    ],
    "level": "A1"
  },
  {
    "id": 80,
    "translations": {
      "en": {
        "text": "of",
        "phonetic": "əv",
        "synonyms": [
          "from"
        ],
        "examples": [
          "cube of meat"
        ]
      },
      "de": {
        "text": "aus",
        "phonetic": "aʊ̯s",
        "synonyms": [
          "von"
        ],
        "examples": [
          "Würfel aus Fleisch"
        ]
      },
      "es": {
        "text": "de",
        "phonetic": "de",
        "synonyms": [
          ""
        ],
        "examples": [
          "dados de carne"
        ]
      }
    },
    "tags": [
      "preposition",
      "basic"
    ],
    "level": "A1"
  },
  {
    "id": 81,
    "translations": {
      "en": {
        "text": "with",
        "phonetic": "wɪð",
        "synonyms": [
          ""
        ],
        "examples": [
          "coffee with milk and sugar"
        ]
      },
      "de": {
        "text": "mit",
        "phonetic": "mɪt",
        "synonyms": [
          ""
        ],
        "examples": [
          "Kaffe mit Milch und Zucker"
        ]
      },
      "es": {
        "text": "con",
        "phonetic": "kon",
        "synonyms": [
          ""
        ],
        "examples": [
          "café con leche y azúcar"
        ]
      }
    },
    "tags": [
      "preposition",
      "basic"
    ],
    "level": "A1"
  },
  {
    "id": 82,
    "translations": {
      "en": {
        "text": "the sandwich",
        "phonetic": "ðə ˈsændwɪtʃ",
        "synonyms": [
          "bread"
        ],
        "examples": [
          "A cheese sandwich"
        ]
      },
      "de": {
        "text": "Das Sandwich",
        "phonetic": "das ˈzɛndvɪtʃ",
        "synonyms": [
          "Brot"
        ],
        "examples": [
          "Ein Käsesandwich"
        ]
      },
      "es": {
        "text": "el sándwich",
        "phonetic": "el ˈsandwitʃ",
        "synonyms": [
          "pan"
        ],
        "examples": [
          "Un sándwich de queso"
        ]
      }
    },
    "tags": [
      "noun",
      "food"
    ],
    "level": "A1"
  },
  {
    "id": 83,
    "translations": {
      "en": {
        "text": "the hamburger",
        "phonetic": "ðə ˈhæmbɜːrɡər",
        "synonyms": [
          "burger",
          ""
        ],
        "examples": [
          "the hamburger is hot."
        ]
      },
      "de": {
        "text": "Der Hamburger",
        "phonetic": "deːɐ̯ ˈhambʊʁɡɐ",
        "synonyms": [
          "Burger"
        ],
        "examples": [
          "Der Hamburger ist heiß."
        ]
      },
      "es": {
        "text": "la hamburguesa",
        "phonetic": "la amβuɾˈɣesa",
        "synonyms": [
          ""
        ],
        "examples": [
          "La hamburguesa está caliente."
        ]
      }
    },
    "tags": [
      "noun",
      "food"
    ],
    "level": "A1"
  },
  {
    "id": 84,
    "translations": {
      "en": {
        "text": "the cup",
        "phonetic": "ðə kʌp",
        "synonyms": [
          "mug"
        ],
        "examples": [
          "a cup of tea"
        ]
      },
      "de": {
        "text": "Die Tasse",
        "phonetic": "diː ˈtasə",
        "synonyms": [
          "Glas",
          "Becher"
        ],
        "examples": [
          "Eine Tasse Tee"
        ]
      },
      "es": {
        "text": "la taza",
        "phonetic": "la ˈtasa",
        "synonyms": [
          "copa",
          "vaso"
        ],
        "examples": [
          "una taza de té"
        ]
      }
    },
    "tags": [
      "noun",
      "kitchen"
    ],
    "level": "A1"
  },
  {
    "id": 85,
    "translations": {
      "en": {
        "text": "the orange",
        "phonetic": "ðə ˈɔːrɪndʒ",
        "synonyms": [
          ""
        ],
        "examples": [
          "The orange is round"
        ]
      },
      "de": {
        "text": "Die Orange",
        "phonetic": "diː oˈʁaŋʒə",
        "synonyms": [
          ""
        ],
        "examples": [
          "Die Orange ist rund"
        ]
      },
      "es": {
        "text": "la naranja",
        "phonetic": "la naˈɾaŋxa",
        "synonyms": [
          ""
        ],
        "examples": [
          "La naranja es redonda."
        ]
      }
    },
    "tags": [
      "noun",
      "food"
    ],
    "level": "A1"
  },
  {
    "id": 86,
    "translations": {
      "en": {
        "text": "the coffee",
        "phonetic": "ðə ˈkɒfi",
        "synonyms": [
          ""
        ],
        "examples": [
          "The coffee is hot"
        ]
      },
      "de": {
        "text": "Der Kaffe",
        "phonetic": "deːɐ̯ kaˈfeː",
        "synonyms": [
          "Schwarzer Bohnensaft"
        ],
        "examples": [
          ""
        ]
      },
      "es": {
        "text": "El café",
        "phonetic": "el kaˈfe",
        "synonyms": [
          ""
        ],
        "examples": [
          "El café está caliente."
        ]
      }
    },
    "tags": [
      "noun",
      "beverage"
    ],
    "level": "A1"
  },
  {
    "id": 87,
    "translations": {
      "en": {
        "text": "the glass",
        "phonetic": "ðə ɡlɑːs",
        "synonyms": [
          "cup"
        ],
        "examples": [
          "A glass with orange juice"
        ]
      },
      "de": {
        "text": "Das Glas",
        "phonetic": "das ɡlaːs",
        "synonyms": [
          "Becher"
        ],
        "examples": [
          "Ein Glas mit Orangensaft"
        ]
      },
      "es": {
        "text": "el vaso",
        "phonetic": "el ˈbaso",
        "synonyms": [
          "copa"
        ],
        "examples": [
          "Un vaso de jugo de naranja."
        ]
      }
    },
    "tags": [
      "noun",
      "kitchen"
    ],
    "level": "A1"
  },
  {
    "id": 88,
    "translations": {
      "en": {
        "text": "the juice",
        "phonetic": "ðə dʒuːs",
        "synonyms": [
          ""
        ],
        "examples": [
          "I'm standing in juice"
        ]
      },
      "de": {
        "text": "Der Saft",
        "phonetic": "deːɐ̯ zaft",
        "synonyms": [
          ""
        ],
        "examples": [
          "Ich steh im Saft"
        ]
      },
      "es": {
        "text": "el jugo",
        "phonetic": "el ˈxuɣo",
        "synonyms": [
          "zumo"
        ],
        "examples": [
          "Estoy en el jugo"
        ]
      }
    },
    "tags": [
      "noun",
      "beverage"
    ],
    "level": "A1"
  },
  {
    "id": 89,
    "translations": {
      "en": {
        "text": "without",
        "phonetic": "wɪˈðaʊt",
        "synonyms": [
          "absent",
          "with no"
        ],
        "examples": [
          "Without you, I am nothing."
        ]
      },
      "de": {
        "text": "ohne",
        "phonetic": "ˈoːnə",
        "synonyms": [
          ""
        ],
        "examples": [
          "Ohne dich, bin ich nichts."
        ]
      },
      "es": {
        "text": "sin",
        "phonetic": "sin",
        "synonyms": [
          ""
        ],
        "examples": [
          "Sin ti no soy nada"
        ]
      }
    },
    "tags": [
      "preposition",
      "basic"
    ],
    "level": "A1"
  },
  {
    "id": 90,
    "translations": {
      "en": {
        "text": "the sugar",
        "phonetic": "ðə ˈʃʊɡər",
        "synonyms": [
          "sweet stuff"
        ],
        "examples": [
          "That's sugar for the heart"
        ]
      },
      "de": {
        "text": "Der Zucker",
        "phonetic": "deːɐ̯ ˈtsʊkɐ",
        "synonyms": [
          "süßes Zeug"
        ],
        "examples": [
          "Das ist Zucker fürs Herz."
        ]
      },
      "es": {
        "text": "el azúcar",
        "phonetic": "el aˈsukar",
        "synonyms": [
          ""
        ],
        "examples": [
          "Es azúcar para el corazón."
        ]
      }
    },
    "tags": [
      "noun",
      "food"
    ],
    "level": "A1"
  },
  {
    "id": 91,
    "translations": {
      "en": {
        "text": "or",
        "phonetic": "ɔːr",
        "synonyms": [
          ""
        ],
        "examples": [
          "With or without milk"
        ]
      },
      "de": {
        "text": "oder",
        "phonetic": "ˈoːdɐ",
        "synonyms": [
          ""
        ],
        "examples": [
          "Mit oder ohne Milch"
        ]
      },
      "es": {
        "text": "o",
        "phonetic": "o",
        "synonyms": [
          ""
        ],
        "examples": [
          "Con o sin leche"
        ]
      }
    },
    "tags": [
      "conjunction",
      "basic"
    ],
    "level": "A1"
  },
  {
    "id": 92,
    "translations": {
      "en": {
        "text": "to pay",
        "phonetic": "tə ˈpeɪ",
        "synonyms": [
          ""
        ],
        "examples": [
          "I'll pay the bill."
        ]
      },
      "de": {
        "text": "bezahlen",
        "phonetic": "bəˈtsaːlən",
        "synonyms": [
          ""
        ],
        "examples": [
          "Ich bezahl die Rechnung"
        ]
      },
      "es": {
        "text": "pagar",
        "phonetic": "paˈɣaɾ",
        "synonyms": [
          ""
        ],
        "examples": [
          "Yo pago la cuenta."
        ]
      }
    },
    "tags": [
      "verb",
      "money"
    ],
    "level": "A1"
  },
  {
    "id": 93,
    "translations": {
      "en": {
        "text": "the salad",
        "phonetic": "ðə ˈsæləd",
        "synonyms": [
          "leaf dish"
        ],
        "examples": [
          "There is corn on my salad."
        ]
      },
      "de": {
        "text": "Der Salat",
        "phonetic": "deːɐ̯ zaˈlaːt",
        "synonyms": [
          "Blättergericht"
        ],
        "examples": [
          "Auf meinem Salat ist Mais"
        ]
      },
      "es": {
        "text": "la ensalada",
        "phonetic": "la ensaˈlaða",
        "synonyms": [
          "plato de hojas"
        ],
        "examples": [
          "Hay maíz en mi ensalada."
        ]
      }
    },
    "tags": [
      "noun",
      "food"
    ],
    "level": "A1"
  },
  {
    "id": 94,
    "translations": {
      "en": {
        "text": "the tomato",
        "phonetic": "ðə təˈmeɪtoʊ",
        "synonyms": [
          "",
          ""
        ],
        "examples": [
          "the tomato is red"
        ]
      },
      "de": {
        "text": "Die Tomate",
        "phonetic": "diː toˈmaːtə",
        "synonyms": [
          ""
        ],
        "examples": [
          "Die Tomate ist rot."
        ]
      },
      "es": {
        "text": "el tomate",
        "phonetic": "el toˈmate",
        "synonyms": [
          ""
        ],
        "examples": [
          "El tomate es rojo."
        ]
      }
    },
    "tags": [
      "noun",
      "food"
    ],
    "level": "A1"
  },
  {
    "id": 95,
    "translations": {
      "en": {
        "text": "want",
        "phonetic": "wɒnt",
        "synonyms": [
          "wish",
          "love"
        ],
        "examples": [
          "I want your heart."
        ]
      },
      "de": {
        "text": "möchten",
        "phonetic": "ˈmœçtən",
        "synonyms": [
          "wollen",
          "wünschen"
        ],
        "examples": [
          "Ich möchte dein Herz"
        ]
      },
      "es": {
        "text": "querer",
        "phonetic": "keˈɾeɾ",
        "synonyms": [
          ""
        ],
        "examples": [
          "Quiero tu corazón"
        ]
      }
    },
    "tags": [
      "verb",
      "basic"
    ],
    "level": "A1"
  },
  {
    "id": 96,
    "translations": {
      "en": {
        "text": "the check",
        "phonetic": "ðə tʃek",
        "synonyms": [
          "bill",
          ""
        ],
        "examples": [
          "I'll pay the bill."
        ]
      },
      "de": {
        "text": "Die Rechnung",
        "phonetic": "diː ˈʁɛçnʊŋ",
        "synonyms": [
          ""
        ],
        "examples": [
          "Ich bezahl die Rechnung."
        ]
      },
      "es": {
        "text": "La cuenta",
        "phonetic": "la ˈkwenta",
        "synonyms": [
          ""
        ],
        "examples": [
          "Yo pago la cuenta."
        ]
      }
    },
    "tags": [
      "noun",
      "money"
    ],
    "level": "A1"
  },
  {
    "id": 97,
    "translations": {
      "en": {
        "text": "the salt",
        "phonetic": "ðə sɔːlt",
        "synonyms": [
          ""
        ],
        "examples": [
          "You still need to add salt."
        ]
      },
      "de": {
        "text": "Das Salz",
        "phonetic": "zalts",
        "synonyms": [
          ""
        ],
        "examples": [
          "Da muss noch Salz rein."
        ]
      },
      "es": {
        "text": "La sal",
        "phonetic": "la sal",
        "synonyms": [
          ""
        ],
        "examples": [
          "Hay que añadir sal."
        ]
      }
    },
    "tags": [
      "noun",
      "food"
    ],
    "level": "A1"
  }
]